{"createdDate":"2020-03-05 16:50:14","id":"420BE9E5-1A0E-4BB0-A873-3AD7361925C6","modifiedDate":"2020-03-14 20:57:32","title":"TrainingData","dataResult":{"itemsCount":780,"columns":["accelerometerAccelerationX(G)","accelerometerAccelerationY(G)","accelerometerAccelerationZ(G)","accelerometerTimestamp_sinceReboot(s)","label(N)","loggingSample(N)"],"dataURL":"file:\/\/\/Users\/horinez\/Documents\/GestureKeyboard-CreateML-Model\/TrainingData\/","columnTypes":["Double","Double","Double","Double","Int","Int"],"classesCount":26,"analysis":{"summary":{"canUseValidation":1,"classCount":26,"sampleCount":780},"issues":[{"description":"26 classes found, including N, A, Q","severity":"info"},{"description":"780 activity recording files found, automatically creating validation set","severity":"good"},{"description":"Smallest class is \"I\" with 30 activity recording files","severity":"warning"},{"description":"Largest class is \"N\" with 30 activity recording files","severity":"info"},{"description":"3 feature columns are selected","severity":"good"}],"classifierAnalysis":{"columns":[],"vizualizerSpec":"","labelStats":{"G":30,"U":30,"H":30,"V":30,"I":30,"W":30,"J":30,"X":30,"K":30,"Y":30,"L":30,"Z":30,"M":30,"N":30,"A":30,"O":30,"B":30,"P":30,"C":30,"Q":30,"D":30,"R":30,"E":30,"S":30,"F":30,"T":30}}},"columnValues":["-0.03, -0.03, -0.06, -0.09, -0.10...","-0.30, -0.27, -0.26, -0.26, -0.27...","-0.95, -0.97, -0.96, -0.97, -0.99...","102,145.71, 102,145.77, 102,145.83, 102,145.89, 102,145.95...","2, 2, 2, 2, 2...","1, 2, 3, 4, 5..."],"error":{"code":1000,"reason":"No feature columns selected","domain":"composer.error.domain","errorType":"notReady"}},"preferredFilename":"TrainingData","version":"1.0","pathType":0,"experimentIDs":["09C920E3-5175-4030-8868-3232DF4CB9EE"]}